client/__init__.py
client/client.py
client/client/__init__.py
client/client/add_contact.py
client/client/database.py
client/client/del_contact.py
client/client/main_window.py
client/client/main_window_conv.py
client/client/start_dialog.py
client/client/transport.py
client/common/__init__.py
client/common/decos.py
client/common/descryptors.py
client/common/errors.py
client/common/metaclasses.py
client/common/utils.py
client/common/variables.py
client/doc/__init__.py
client/doc/source/__init__.py
client/doc/source/conf.py
client/logs/__init__.py
client/logs/client_log_config.py
client/logs/server_log_config.py
client/unit_tests/__init__.py
client_chat_pyqt_march_24-0.0.1.dist-info/METADATA
client_chat_pyqt_march_24-0.0.1.dist-info/WHEEL
client_chat_pyqt_march_24-0.0.1.dist-info/top_level.txt
client_chat_pyqt_march_24-0.0.1.dist-info/RECORD
