Metadata-Version: 2.1
Name: client-chat-pyqt-march-24
Version: 0.0.1
Summary: messenger_client_part
Author: Grigoriev Sergey
Author-email: my_email@yandex.ru
License: UNKNOWN
Platform: UNKNOWN
Requires-Dist: PyQt5
Requires-Dist: sqlalchemy
Requires-Dist: pycryptodome
Requires-Dist: pycryptodomex
